src/__init__.py
oreilly_book_echo-0.1.0.dist-info/METADATA
oreilly_book_echo-0.1.0.dist-info/WHEEL
oreilly_book_echo-0.1.0.dist-info/RECORD
